QLGR/__init__.py
QLGR/handler.py
QLGR/main.py
queue_logger-0.0.4.dist-info/LICENSE
queue_logger-0.0.4.dist-info/METADATA
queue_logger-0.0.4.dist-info/WHEEL
queue_logger-0.0.4.dist-info/top_level.txt
queue_logger-0.0.4.dist-info/RECORD
