Metadata-Version: 2.1
Name: queue-logger
Version: 0.0.4
Summary: Python logger with custom handler for rabbitmq
Author-email: Amirreza Taherkhani <amirrezataherkhaani@gmail.com>
Project-URL: Homepage, https://github.com/Visapick-Team/QLGR
Project-URL: Issues, https://github.com/Visapick-Team/QLGR/issues
Classifier: Programming Language :: Python :: 3
Classifier: License :: OSI Approved :: GNU General Public License v3 or later (GPLv3+)
Classifier: Operating System :: OS Independent
Requires-Python: >=3.8
License-File: LICENSE
Requires-Dist: pika ==1.3.2
